sopel_wolfram/__init__.py
sopel_wolfram/plugin.py
sopel_wolfram/vendor/__init__.py
sopel_wolfram/vendor/wolframalpha.py
sopel_wolfram-0.6.1.dist-info/licenses/COPYING
sopel_wolfram-0.6.1.dist-info/METADATA
sopel_wolfram-0.6.1.dist-info/WHEEL
sopel_wolfram-0.6.1.dist-info/entry_points.txt
sopel_wolfram-0.6.1.dist-info/top_level.txt
sopel_wolfram-0.6.1.dist-info/RECORD
