Metadata-Version: 2.4
Name: sopel-wolfram
Version: 0.6.1
Summary: Wolfram|Alpha plugin for the Sopel IRC bot framework
Author-email: Max Gurela <maxpowa1@gmail.com>
Maintainer-email: dgw <dgw@technobabbl.es>
License-Expression: EFL-2.0
Project-URL: Homepage, https://github.com/dgw/sopel-wolfram
Project-URL: Bug Tracker, https://github.com/dgw/sopel-wolfram/issues
Keywords: sopel,plugin,bot,irc
Platform: Linux x86, x86-64
Classifier: Development Status :: 5 - Production/Stable
Classifier: Intended Audience :: Developers
Classifier: Intended Audience :: System Administrators
Classifier: Programming Language :: Python :: 3 :: Only
Classifier: Programming Language :: Python :: 3.8
Classifier: Programming Language :: Python :: 3.9
Classifier: Programming Language :: Python :: 3.10
Classifier: Programming Language :: Python :: 3.11
Classifier: Programming Language :: Python :: 3.12
Classifier: Programming Language :: Python :: 3.13
Classifier: Programming Language :: Python :: 3.14
Classifier: Topic :: Communications :: Chat :: Internet Relay Chat
Requires-Python: <4,>=3.8
License-File: COPYING
Requires-Dist: sopel~=8.0
Requires-Dist: xmltodict
Requires-Dist: more_itertools
Requires-Dist: jaraco.context
Requires-Dist: httpx
Requires-Dist: multidict
Dynamic: license-file
